[{"Name":"Advanced Custom Fields PRO","PluginURI":"https://www.advancedcustomfields.com/","Version":"5.7.10","Description":"Customize WordPress with powerful, professional and intuitive fields.","Author":"Elliot Condon","AuthorURI":"http://www.elliotcondon.com/","TextDomain":"acf","DomainPath":"/lang","Network":false,"Title":"Advanced Custom Fields PRO","AuthorName":"Elliot Condon","id":"advanced-custom-fields-pro/acf.php"},{"Name":"Custom Post Type UI","PluginURI":"https://github.com/WebDevStudios/custom-post-type-ui/","Version":"1.6.1","Description":"Admin panel for creating custom post types and custom taxonomies in WordPress","Author":"WebDevStudios","AuthorURI":"https://webdevstudios.com/","TextDomain":"custom-post-type-ui","DomainPath":"/languages","Network":false,"Title":"Custom Post Type UI","AuthorName":"WebDevStudios","id":"custom-post-type-ui/custom-post-type-ui.php"},{"Name":"Post Type Select for Advanced Custom Fields","PluginURI":"https://github.com/Clark-Nikdel-Powell/Post-Type-Select-for-ACF","Version":"1.1.0","Description":"Custom field definition for Advanced Custom Fields for a select box populated with post types.","Author":"Glenn Welser","AuthorURI":"https://clarknikdelpowell.com/agency/people/glenn","TextDomain":"post-type-select-for-advanced-custom-fields","DomainPath":"","Network":false,"Title":"Post Type Select for Advanced Custom Fields","AuthorName":"Glenn Welser","id":"post-type-select-for-advanced-custom-fields/acf-posttype-select.php"},{"Name":"Yoast SEO","PluginURI":"https://yoa.st/1uj","Version":"9.6","Description":"The first true all-in-one SEO solution for WordPress, including on-page content analysis, XML sitemaps and much more.","Author":"Team Yoast","AuthorURI":"https://yoa.st/1uk","TextDomain":"wordpress-seo","DomainPath":"/languages/","Network":false,"Title":"Yoast SEO","AuthorName":"Team Yoast","id":"wordpress-seo/wp-seo.php"}]